bitrix_mcp/__init__.py
bitrix_mcp/__main__.py
bitrix_mcp/server.py
bitrix_mcp/bitrix/__init__.py
bitrix_mcp/bitrix/client.py
bitrix_mcp/bitrix/types.py
bitrix24_lkp_mcp-0.2.1.dist-info/METADATA
bitrix24_lkp_mcp-0.2.1.dist-info/WHEEL
bitrix24_lkp_mcp-0.2.1.dist-info/entry_points.txt
bitrix24_lkp_mcp-0.2.1.dist-info/licenses/LICENSE
bitrix24_lkp_mcp-0.2.1.dist-info/RECORD
