Metadata-Version: 2.4
Name: bitrix24-lkp-mcp
Version: 0.2.1
Summary: MCP server for Bitrix24 task planning - enables AI assistants to help break down tasks into subtasks
Project-URL: Homepage, https://github.com/lamkimphu258/bitrix24-lkp-mcp
Project-URL: Repository, https://github.com/lamkimphu258/bitrix24-lkp-mcp
Project-URL: Issues, https://github.com/lamkimphu258/bitrix24-lkp-mcp/issues
Author-email: LKP <lamkimphu258@gmail.com>
License-Expression: MIT
License-File: LICENSE
Keywords: ai-assistant,bitrix24,mcp,scrum,task-management
Classifier: Development Status :: 4 - Beta
Classifier: Intended Audience :: Developers
Classifier: License :: OSI Approved :: MIT License
Classifier: Programming Language :: Python :: 3
Classifier: Programming Language :: Python :: 3.11
Classifier: Programming Language :: Python :: 3.12
Requires-Python: >=3.11
Requires-Dist: fastmcp>=2.0.0
Requires-Dist: httpx>=0.27.0
Requires-Dist: pydantic>=2.0.0
Provides-Extra: dev
Requires-Dist: pytest-asyncio>=0.24.0; extra == 'dev'
Requires-Dist: pytest>=8.0.0; extra == 'dev'
Requires-Dist: respx>=0.21.0; extra == 'dev'
Requires-Dist: ruff>=0.4.0; extra == 'dev'
